blamegame/BlameFrame.py
blamegame/__init__.py
blamegame-0.0.1.dist-info/METADATA
blamegame-0.0.1.dist-info/WHEEL
blamegame-0.0.1.dist-info/top_level.txt
blamegame-0.0.1.dist-info/RECORD
